flootstrap/__init__.py
flootstrap/bootstrapper.py
flootstrap/bootstrappers/__init__.py
flootstrap/bootstrappers/debootstrap.py
flootstrap/bootstrappers/rinse.py
flootstrap/logger.py
flootstrap/main.py
flootstrap/utils.py
flootstrap-0.1.0.dist-info/METADATA
flootstrap-0.1.0.dist-info/WHEEL
flootstrap-0.1.0.dist-info/entry_points.txt
flootstrap-0.1.0.dist-info/RECORD
