Metadata-Version: 2.1
Name: flootstrap
Version: 0.1.0
Summary: Linux Bootstrapper
Author: Fluendo S.A.
Author-email: support@fluendo.com
Requires-Python: >=3.10,<4.0
Classifier: Programming Language :: Python
Classifier: Programming Language :: Python :: 3
Classifier: Programming Language :: Python :: 3.10
Classifier: Programming Language :: Python :: 3.11
Classifier: Programming Language :: Python :: 3.12
Requires-Dist: colorlog (>=6.8.2,<7.0.0)
Requires-Dist: tomli (>=2.0.1,<3.0.0)
